{"data":[{"date":"2009","country":"United States","amount":"18.69 million bbl\/day"},{"date":"2009","country":"European Union","amount":"13.63 million bbl\/day"},{"date":"2009","country":"China","amount":"8.2 million bbl\/day"},{"date":"2009","country":"Group of 7 countries (G7) average","amount":"4.67 million bbl\/day"},{"date":"2009","country":"Japan","amount":"4.36 million bbl\/day"},{"date":"2009","country":"India","amount":"2.98 million bbl\/day"},{"date":"2010","country":"Russia","amount":"2.74 million bbl\/day"},{"date":"2009","country":"Brazil","amount":"2.46 million bbl\/day"},{"date":"2009","country":"Germany","amount":"2.44 million bbl\/day"},{"date":"2009","country":"Saudi Arabia","amount":"2.43 million bbl\/day"},{"date":"2010","country":"South Korea","amount":"2.19 million bbl\/day"},{"date":"2009","country":"Canada","amount":"2.15 million bbl\/day"},{"date":"2009","country":"Mexico","amount":"2.08 million bbl\/day"},{"date":"2009","country":"France","amount":"1.88 million bbl\/day"},{"date":"2009","country":"Iran","amount":"1.81 million bbl\/day"},{"date":"2009","country":"Non-religious countries average","amount":"1.69 million bbl\/day"},{"date":"2009","country":"United Kingdom","amount":"1.67 million bbl\/day"},{"date":"2009","country":"Italy","amount":"1.54 million bbl\/day"},{"date":"2009","country":"Spain","amount":"1.48 million bbl\/day"},{"date":"2009","country":"High income OECD countries average","amount":"1.35 million bbl\/day"},{"date":"2009","country":"Indonesia","amount":"1.11 million bbl\/day"},{"date":"2009","country":"Emerging markets average","amount":"1.03 million bbl\/day"},{"date":"2009","country":"Cold countries average","amount":"1.02 million bbl\/day"},{"date":"2009","country":"Heavily indebted countries average","amount":"966,663.41 bbl\/day"},{"date":"2009","country":"Australia","amount":"946,300 bbl\/day"},{"date":"2009","country":"Singapore","amount":"927,000 bbl\/day"},{"date":"2009","country":"Netherlands","amount":"922,800 bbl\/day"},{"date":"2009","country":"South Asia average","amount":"839,750 bbl\/day"},{"date":"2010","country":"Taiwan","amount":"834,000 bbl\/day"},{"date":"2009","country":"Venezuela","amount":"740,000 bbl\/day"},{"date":"2009","country":"Iraq","amount":"687,000 bbl\/day"},{"date":"2009","country":"OPEC countries average","amount":"683,454.55 bbl\/day"},{"date":"2009","country":"Egypt","amount":"683,000 bbl\/day"},{"date":"2009","country":"Argentina","amount":"622,000 bbl\/day"},{"date":"2009","country":"NATO countries average","amount":"611,778.85 bbl\/day"},{"date":"2009","country":"Former British colonies average","amount":"609,579.59 bbl\/day"},{"date":"2009","country":"Belgium","amount":"608,200 bbl\/day"},{"date":"2009","country":"Eurozone average","amount":"583,447.22 bbl\/day"},{"date":"2009","country":"Turkey","amount":"579,500 bbl\/day"},{"date":"2009","country":"South Africa","amount":"579,000 bbl\/day"},{"date":"2009","country":"Poland","amount":"545,400 bbl\/day"},{"date":"2009","country":"Religious countries average","amount":"544,780.95 bbl\/day"},{"date":"2009","country":"Malaysia","amount":"536,000 bbl\/day"},{"date":"2009","country":"European Union average","amount":"516,209.26 bbl\/day"},{"date":"2001","country":"Europe average","amount":"471,513.41 bbl\/day"},{"date":"2009","country":"Christian countries average","amount":"463,751.63 bbl\/day"},{"date":"2009","country":"Middle Eastern and North Africa average","amount":"463,666.67 bbl\/day"},{"date":"2009","country":"United Arab Emirates","amount":"435,000 bbl\/day"},{"date":"2009","country":"Greece","amount":"414,400 bbl\/day"},{"date":"2009","country":"Catholic countries average","amount":"403,275 bbl\/day"},{"date":"2009","country":"Pakistan","amount":"373,000 bbl\/day"},{"date":"2009","country":"Hong Kong","amount":"359,000 bbl\/day"},{"date":"2009","country":"Thailand","amount":"356,000 bbl\/day"},{"date":"2009","country":"Ukraine","amount":"348,000 bbl\/day"},{"date":"2009","country":"South and Central Asia average","amount":"336,000 bbl\/day"},{"date":"2009","country":"Sweden","amount":"328,100 bbl\/day"},{"date":"2009","country":"Algeria","amount":"325,000 bbl\/day"},{"date":"2009","country":"Kuwait","amount":"320,000 bbl\/day"},{"date":"2010","country":"Vietnam","amount":"311,400 bbl\/day"},{"date":"2010","country":"Philippines","amount":"307,200 bbl\/day"},{"date":"2009","country":"Former Spanish colonies average","amount":"294,411.76 bbl\/day"},{"date":"2009","country":"Colombia","amount":"288,000 bbl\/day"},{"date":"2009","country":"Libya","amount":"280,000 bbl\/day"},{"date":"2009","country":"Nigeria","amount":"280,000 bbl\/day"},{"date":"2009","country":"Switzerland","amount":"280,000 bbl\/day"},{"date":"2009","country":"Chile","amount":"277,000 bbl\/day"},{"date":"2001","country":"Eastern Europe average","amount":"272,494.12 bbl\/day"},{"date":"2009","country":"Portugal","amount":"272,200 bbl\/day"},{"date":"2009","country":"Muslim countries average","amount":"265,766.67 bbl\/day"},{"date":"2009","country":"Syria","amount":"252,000 bbl\/day"},{"date":"2009","country":"Austria","amount":"247,700 bbl\/day"},{"date":"2009","country":"Kazakhstan","amount":"241,000 bbl\/day"},{"date":"2009","country":"Israel","amount":"231,000 bbl\/day"},{"date":"2001","country":"Sparsely populated countries average","amount":"226,812.37 bbl\/day"},{"date":"2009","country":"Latin America and Caribbean average","amount":"226,558.82 bbl\/day"},{"date":"2009","country":"Romania","amount":"214,000 bbl\/day"},{"date":"2009","country":"Hot countries average","amount":"212,735.05 bbl\/day"},{"date":"2009","country":"Czech Republic","amount":"207,600 bbl\/day"},{"date":"2009","country":"Finland","amount":"206,200 bbl\/day"},{"date":"2009","country":"Norway","amount":"204,100 bbl\/day"},{"date":"2009","country":"Morocco","amount":"187,000 bbl\/day"},{"date":"2009","country":"Ecuador","amount":"181,000 bbl\/day"},{"date":"2009","country":"Belarus","amount":"173,000 bbl\/day"},{"date":"2009","country":"Cuba","amount":"169,000 bbl\/day"},{"date":"2009","country":"Denmark","amount":"166,500 bbl\/day"},{"date":"2009","country":"Puerto Rico","amount":"164,100 bbl\/day"},{"date":"2009","country":"Ireland","amount":"160,900 bbl\/day"},{"date":"2009","country":"Peru","amount":"157,000 bbl\/day"},{"date":"2009","country":"Yemen","amount":"155,000 bbl\/day"},{"date":"2009","country":"New Zealand","amount":"154,100 bbl\/day"},{"date":"2009","country":"Uzbekistan","amount":"145,000 bbl\/day"},{"date":"2009","country":"Qatar","amount":"142,000 bbl\/day"},{"date":"2010","country":"Hungary","amount":"137,300 bbl\/day"},{"date":"2009","country":"Azerbaijan","amount":"136,000 bbl\/day"},{"date":"2009","country":"Bulgaria","amount":"125,000 bbl\/day"},{"date":"2009","country":"Turkmenistan","amount":"120,000 bbl\/day"},{"date":"2009","country":"Dominican Republic","amount":"118,000 bbl\/day"},{"date":"2009","country":"failed states average","amount":"110,733.33 bbl\/day"},{"date":"2009","country":"Jordan","amount":"108,000 bbl\/day"},{"date":"2009","country":"Croatia","amount":"106,000 bbl\/day"},{"date":"2009","country":"Former Soviet republics average","amount":"102,928.57 bbl\/day"},{"date":"2009","country":"Panama","amount":"93,000 bbl\/day"},{"date":"2009","country":"Serbia and Montenegro","amount":"90,000 bbl\/day"},{"date":"2009","country":"Lebanon","amount":"90,000 bbl\/day"},{"date":"2009","country":"Sri Lanka","amount":"90,000 bbl\/day"},{"date":"2009","country":"Tunisia","amount":"89,000 bbl\/day"},{"date":"2009","country":"Virgin Islands","amount":"88,820 bbl\/day"},{"date":"2009","country":"Sudan","amount":"84,000 bbl\/day"},{"date":"2009","country":"Oman","amount":"84,000 bbl\/day"},{"date":"2010","country":"Bangladesh","amount":"82,340 bbl\/day"},{"date":"2009","country":"Slovakia","amount":"79,930 bbl\/day"},{"date":"2009","country":"Guatemala","amount":"79,000 bbl\/day"},{"date":"2009","country":"Jamaica","amount":"77,000 bbl\/day"},{"date":"2009","country":"Kenya","amount":"76,000 bbl\/day"},{"date":"2009","country":"Lithuania","amount":"74,000 bbl\/day"},{"date":"2009","country":"Angola","amount":"70,000 bbl\/day"},{"date":"2006","country":"Netherlands Antilles","amount":"67,450 bbl\/day"},{"date":"2009","country":"Slovenia","amount":"60,000 bbl\/day"},{"date":"2010","country":"Bolivia","amount":"59,000 bbl\/day"},{"date":"2009","country":"Cyprus","amount":"59,000 bbl\/day"},{"date":"2009","country":"Ghana","amount":"57,000 bbl\/day"},{"date":"2009","country":"Honduras","amount":"56,000 bbl\/day"},{"date":"2009","country":"Former French colonies average","amount":"52,608.7 bbl\/day"},{"date":"2009","country":"Luxembourg","amount":"50,720 bbl\/day"},{"date":"2009","country":"Armenia","amount":"49,000 bbl\/day"},{"date":"2009","country":"El Salvador","amount":"46,000 bbl\/day"},{"date":"2009","country":"Costa Rica","amount":"44,000 bbl\/day"},{"date":"2009","country":"Trinidad and Tobago","amount":"43,000 bbl\/day"},{"date":"2009","country":"Burma","amount":"42,000 bbl\/day"},{"date":"2009","country":"Latvia","amount":"40,000 bbl\/day"},{"date":"2010","country":"Uruguay","amount":"40,000 bbl\/day"},{"date":"2009","country":"Bahrain","amount":"39,000 bbl\/day"},{"date":"2009","country":"Senegal","amount":"39,000 bbl\/day"},{"date":"2009","country":"Ethiopia","amount":"38,000 bbl\/day"},{"date":"2009","country":"Tajikistan","amount":"38,000 bbl\/day"},{"date":"2009","country":"Papua New Guinea","amount":"36,000 bbl\/day"},{"date":"2009","country":"The Bahamas","amount":"36,000 bbl\/day"},{"date":"2009","country":"Albania","amount":"36,000 bbl\/day"},{"date":"2009","country":"Sub-Saharan Africa average","amount":"34,936.17 bbl\/day"},{"date":"2009","country":"Tanzania","amount":"34,000 bbl\/day"},{"date":"2009","country":"Bosnia and Herzegovina","amount":"30,000 bbl\/day"},{"date":"2009","country":"Estonia","amount":"30,000 bbl\/day"},{"date":"2009","country":"Nicaragua","amount":"29,000 bbl\/day"},{"date":"2009","country":"Paraguay","amount":"27,000 bbl\/day"},{"date":"2009","country":"Cameroon","amount":"26,000 bbl\/day"},{"date":"2009","country":"Cote d'Ivoire","amount":"24,000 bbl\/day"},{"date":"2009","country":"Mauritius","amount":"23,000 bbl\/day"},{"date":"2009","country":"Benin","amount":"23,000 bbl\/day"},{"date":"2009","country":"Namibia","amount":"22,000 bbl\/day"},{"date":"2009","country":"Madagascar","amount":"21,000 bbl\/day"},{"date":"2009","country":"Gibraltar","amount":"21,000 bbl\/day"},{"date":"2009","country":"Togo","amount":"21,000 bbl\/day"},{"date":"2009","country":"Mauritania","amount":"20,000 bbl\/day"},{"date":"2009","country":"Moldova","amount":"19,000 bbl\/day"},{"date":"2009","country":"Malta","amount":"19,000 bbl\/day"},{"date":"2009","country":"Iceland","amount":"18,900 bbl\/day"},{"date":"2003","country":"Reunion","amount":"18,500 bbl\/day"},{"date":"2009","country":"Nepal","amount":"18,000 bbl\/day"},{"date":"2009","country":"Mozambique","amount":"18,000 bbl\/day"},{"date":"2009","country":"Macau","amount":"16,000 bbl\/day"},{"date":"2009","country":"Mongolia","amount":"16,000 bbl\/day"},{"date":"2009","country":"Brunei","amount":"16,000 bbl\/day"},{"date":"2009","country":"Zambia","amount":"16,000 bbl\/day"},{"date":"2009","country":"North Korea","amount":"16,000 bbl\/day"},{"date":"2009","country":"Botswana","amount":"15,000 bbl\/day"},{"date":"2009","country":"Kyrgyzstan","amount":"15,000 bbl\/day"},{"date":"2009","country":"Suriname","amount":"14,000 bbl\/day"},{"date":"2009","country":"Gabon","amount":"14,000 bbl\/day"},{"date":"2003","country":"Martinique","amount":"13,800 bbl\/day"},{"date":"2009","country":"Georgia","amount":"13,000 bbl\/day"},{"date":"2003","country":"Guadeloupe","amount":"13,000 bbl\/day"},{"date":"2009","country":"Uganda","amount":"13,000 bbl\/day"},{"date":"2009","country":"New Caledonia","amount":"13,000 bbl\/day"},{"date":"2009","country":"Haiti","amount":"12,000 bbl\/day"},{"date":"2009","country":"Djibouti","amount":"12,000 bbl\/day"},{"date":"2009","country":"Fiji","amount":"11,000 bbl\/day"},{"date":"2009","country":"Zimbabwe","amount":"11,000 bbl\/day"},{"date":"2009","country":"Guam","amount":"10,620 bbl\/day"},{"date":"2009","country":"Congo, Republic of the","amount":"10,000 bbl\/day"},{"date":"2009","country":"Democratic Republic of the Congo","amount":"10,000 bbl\/day"},{"date":"2009","country":"Guyana","amount":"10,000 bbl\/day"},{"date":"2009","country":"Burkina Faso","amount":"9,000 bbl\/day"},{"date":"2009","country":"Barbados","amount":"9,000 bbl\/day"},{"date":"2009","country":"Guinea","amount":"9,000 bbl\/day"},{"date":"2009","country":"Sierra Leone","amount":"9,000 bbl\/day"},{"date":"2009","country":"Malawi","amount":"8,000 bbl\/day"},{"date":"2009","country":"Aruba","amount":"8,000 bbl\/day"},{"date":"2009","country":"Belize","amount":"7,000 bbl\/day"},{"date":"2009","country":"French Polynesia","amount":"7,000 bbl\/day"},{"date":"2009","country":"Seychelles","amount":"7,000 bbl\/day"},{"date":"2003","country":"French Guiana","amount":"6,600 bbl\/day"},{"date":"2009","country":"Rwanda","amount":"6,000 bbl\/day"},{"date":"2009","country":"Maldives","amount":"6,000 bbl\/day"},{"date":"2009","country":"Mali","amount":"6,000 bbl\/day"},{"date":"2009","country":"Niger","amount":"6,000 bbl\/day"},{"date":"2009","country":"Afghanistan","amount":"5,000 bbl\/day"},{"date":"2009","country":"Eritrea","amount":"5,000 bbl\/day"},{"date":"2009","country":"Bermuda","amount":"5,000 bbl\/day"},{"date":"2009","country":"Somalia","amount":"5,000 bbl\/day"},{"date":"2009","country":"Faroe Islands","amount":"5,000 bbl\/day"},{"date":"2009","country":"Antigua and Barbuda","amount":"5,000 bbl\/day"},{"date":"2009","country":"Swaziland","amount":"4,000 bbl\/day"},{"date":"2009","country":"Liberia","amount":"4,000 bbl\/day"},{"date":"2009","country":"American Samoa","amount":"4,000 bbl\/day"},{"date":"2009","country":"Cambodia","amount":"4,000 bbl\/day"},{"date":"2009","country":"Greenland","amount":"4,000 bbl\/day"},{"date":"2009","country":"Saint Lucia","amount":"3,000 bbl\/day"},{"date":"2009","country":"Cayman Islands","amount":"3,000 bbl\/day"},{"date":"2009","country":"Guinea-Bissau","amount":"3,000 bbl\/day"},{"date":"2009","country":"Grenada","amount":"3,000 bbl\/day"},{"date":"2009","country":"Burundi","amount":"3,000 bbl\/day"},{"date":"2009","country":"East Timor","amount":"2,500 bbl\/day"},{"date":"2009","country":"Central African Republic","amount":"2,000 bbl\/day"},{"date":"2009","country":"The Gambia","amount":"2,000 bbl\/day"},{"date":"2009","country":"Cape Verde","amount":"2,000 bbl\/day"},{"date":"2009","country":"Lesotho","amount":"2,000 bbl\/day"},{"date":"2009","country":"Saint Vincent and the Grenadines","amount":"2,000 bbl\/day"},{"date":"2009","country":"Solomon Islands","amount":"2,000 bbl\/day"},{"date":"2010","country":"Laos","amount":"1,918 bbl\/day"},{"date":"2006","country":"Western Sahara","amount":"1,760 bbl\/day"},{"date":"2009","country":"Saint Pierre and Miquelon","amount":"1,000 bbl\/day"},{"date":"2009","country":"Dominica","amount":"1,000 bbl\/day"},{"date":"2009","country":"Vanuatu","amount":"1,000 bbl\/day"},{"date":"2009","country":"Nauru","amount":"1,000 bbl\/day"},{"date":"2009","country":"Sao Tome and Principe","amount":"1,000 bbl\/day"},{"date":"2009","country":"Samoa","amount":"1,000 bbl\/day"},{"date":"2009","country":"Equatorial Guinea","amount":"1,000 bbl\/day"},{"date":"2009","country":"Cook Islands","amount":"1,000 bbl\/day"},{"date":"2009","country":"Saint Kitts and Nevis","amount":"1,000 bbl\/day"},{"date":"2009","country":"Tonga","amount":"1,000 bbl\/day"},{"date":"2009","country":"British Virgin Islands","amount":"1,000 bbl\/day"},{"date":"2009","country":"Chad","amount":"1,000 bbl\/day"},{"date":"2009","country":"Bhutan","amount":"1,000 bbl\/day"},{"date":"2009","country":"Montserrat","amount":"1,000 bbl\/day"},{"date":"2009","country":"Comoros","amount":"1,000 bbl\/day"},{"date":"2006","country":"Kiribati","amount":"232.4 bbl\/day"},{"date":"2006","country":"Saint Helena","amount":"60 bbl\/day"},{"date":"2006","country":"Niue","amount":"20 bbl\/day"},{"date":"2009","country":"Turks and Caicos Islands","amount":"0.0"},{"date":"2009","country":"Falkland Islands (Islas Malvinas)","amount":"0.0"}]}